[
    {
        "confirmed": 1,
        "date": "2026-04-21T13:45:00+02:00",
        "date_ts": 1776771900,
        "description": "30 Minuten vor Abholung anrufen",
        "signUpDate": "2026-04-19 12:03:09",
        "profile": {
            "id": 127590,
            "name": "Christoph Schlimm",
            "avatar": "/api/uploads/e64604e4-0862-4a16-a920-d1c510da2388",
            "isSleeping": 0,
            "mobile": "+49 171 1923338",
            "landline": "+49 6131 8863293",
            "isManager": false
        }
    },
    {
        "confirmed": 1,
        "date": "2026-04-28T13:45:00+02:00",
        "date_ts": 1777376700,
        "description": "30 Minuten vor Abholung anrufen",
        "signUpDate": "2026-04-19 12:11:20",
        "profile": {
            "id": 127590,
            "name": "Christoph Schlimm",
            "avatar": "/api/uploads/e64604e4-0862-4a16-a920-d1c510da2388",
            "isSleeping": 0,
            "mobile": "+49 171 1923338",
            "landline": "+49 6131 8863293",
            "isManager": false
        }
    }
]